pixelfirm/__init__.py
pixelfirm/__main__ .py
pixelfirm/cli.py
pixelfirm/downloader.py
pixelfirm/manifest.json
pixelfirm/manifest_utils.py
pixelfirm/__pycache__/__init__.cpython-312.pyc
pixelfirm/__pycache__/cli.cpython-312.pyc
pixelfirm/__pycache__/downloader.cpython-312.pyc
pixelfirm-1.0.2.dist-info/licenses/LICENSE
pixelfirm-1.0.2.dist-info/METADATA
pixelfirm-1.0.2.dist-info/WHEEL
pixelfirm-1.0.2.dist-info/top_level.txt
pixelfirm-1.0.2.dist-info/RECORD
