Metadata-Version: 2.4
Name: pixelfirm
Version: 1.0.2
Summary: PixelFirm — Android firmware helper tool
Home-page: https://github.com/Android-Artisan/PixelFirm
Author: Android Artisan
Author-email: Android Artisan <romartisan2025@gmail.com>
License:                     GNU GENERAL PUBLIC LICENSE
Project-URL: Homepage, https://github.com/Android-Artisan/PixelFirm
Project-URL: BugTracker, https://github.com/Android-Artisan/PixelFirm/issues
Requires-Python: >=3.7
License-File: LICENSE
Requires-Dist: requests
Requires-Dist: click
Dynamic: author
Dynamic: home-page
Dynamic: license-file
Dynamic: requires-python
